{
	"configurations" : 
	[
		{
			"directories" : 
			[
				{
					"build" : ".",
					"jsonFile" : "directory-.-Debug-f5ebdc15457944623624.json",
					"minimumCMakeVersion" : 
					{
						"string" : "3.10"
					},
					"projectIndex" : 0,
					"source" : ".",
					"targetIndexes" : 
					[
						0
					]
				}
			],
			"name" : "Debug",
			"projects" : 
			[
				{
					"directoryIndexes" : 
					[
						0
					],
					"name" : "MyProject",
					"targetIndexes" : 
					[
						0
					]
				}
			],
			"targets" : 
			[
				{
					"directoryIndex" : 0,
					"id" : "damien::@6890427a1f51a3e7e1df",
					"jsonFile" : "target-damien-Debug-fe1434847b32e6356bd5.json",
					"name" : "damien",
					"projectIndex" : 0
				}
			]
		}
	],
	"kind" : "codemodel",
	"paths" : 
	{
		"build" : "/Users/sprockeelsd/Documents/GiL/GiL_Framework/c++/cmake-build-debug",
		"source" : "/Users/sprockeelsd/Documents/GiL/GiL_Framework/c++"
	},
	"version" : 
	{
		"major" : 2,
		"minor" : 4
	}
}
